appngizer/elements.py
appngizer/client.py
appngizer/appngizer.xsd
appngizer/cli.py
appngizer/__init__.py
appngizer/errors.py
appngizer/utils/__init__.py
appngizer/utils/xmljson/__init__.py
appngizer-1.15.0.data/data/share/man/man1/appngizer.1
appngizer-1.15.0.data/data/share/doc/python-appngizer/html/searchindex.js
appngizer-1.15.0.data/data/share/doc/python-appngizer/html/license.html
appngizer-1.15.0.data/data/share/doc/python-appngizer/html/search.html
appngizer-1.15.0.data/data/share/doc/python-appngizer/html/objects.inv
appngizer-1.15.0.data/data/share/doc/python-appngizer/html/py-modindex.html
appngizer-1.15.0.data/data/share/doc/python-appngizer/html/index.html
appngizer-1.15.0.data/data/share/doc/python-appngizer/html/.buildinfo
appngizer-1.15.0.data/data/share/doc/python-appngizer/html/changes.html
appngizer-1.15.0.data/data/share/doc/python-appngizer/html/authors.html
appngizer-1.15.0.data/data/share/doc/python-appngizer/html/genindex.html
appngizer-1.15.0.data/data/share/doc/python-appngizer/html/api/appngizer.utils.xmljson.html
appngizer-1.15.0.data/data/share/doc/python-appngizer/html/api/modules.html
appngizer-1.15.0.data/data/share/doc/python-appngizer/html/api/appngizer.html
appngizer-1.15.0.data/data/share/doc/python-appngizer/html/api/appngizer.utils.html
appngizer-1.15.0.data/data/share/doc/python-appngizer/html/usage/usage_client.html
appngizer-1.15.0.data/data/share/doc/python-appngizer/html/usage/index.html
appngizer-1.15.0.data/data/share/doc/python-appngizer/html/usage/usage_module.html
appngizer-1.15.0.data/data/share/doc/python-appngizer/html/_modules/collections.html
appngizer-1.15.0.data/data/share/doc/python-appngizer/html/_modules/index.html
appngizer-1.15.0.data/data/share/doc/python-appngizer/html/_modules/appngizer/elements.html
appngizer-1.15.0.data/data/share/doc/python-appngizer/html/_modules/appngizer/client.html
appngizer-1.15.0.dist-info/metadata.json
appngizer-1.15.0.dist-info/METADATA
appngizer-1.15.0.dist-info/WHEEL
appngizer-1.15.0.dist-info/RECORD
appngizer-1.15.0.dist-info/entry_points.txt
appngizer-1.15.0.dist-info/DESCRIPTION.rst
appngizer-1.15.0.dist-info/top_level.txt
