Metadata-Version: 2.0
Name: appngizer
Version: 1.15.0
Summary: Python library for appNGizer webapplication
Home-page: https://github.com/appNG/python-appngizer
Author: aiticon GmbH
Author-email: info@aiticon.de
License: apache
Platform: UNKNOWN
Classifier: Programming Language :: Python
Classifier: Programming Language :: Python :: 2.7
Classifier: Development Status :: 4 - Beta
Classifier: Intended Audience :: Developers
Classifier: Intended Audience :: System Administrators
Classifier: License :: OSI Approved :: Apache Software License
Classifier: Topic :: Software Development :: Libraries :: Python Modules
Requires-Dist: PyYAML (==3.11)
Requires-Dist: argparse (==1.2.1)
Requires-Dist: bcrypt (==3.1.3)
Requires-Dist: beautifulsoup (==3.2.1)
Requires-Dist: certifi (==2017.7.27.1)
Requires-Dist: cffi (==1.9.1)
Requires-Dist: chardet (==3.0.4)
Requires-Dist: idna (==2.0)
Requires-Dist: lxml (==3.4.0)
Requires-Dist: py-bcrypt (==0.4)
Requires-Dist: pycparser (==2.10)
Requires-Dist: requests (==2.4.3)
Requires-Dist: six (==1.8.0)
Requires-Dist: urllib3 (==1.9.1)
